shapix/__init__.py
shapix/cli.py
shapix/core/__init__.py
shapix/core/base.py
shapix/rendering/__init__.py
shapix/rendering/renderer.py
shapix/shapes/__init__.py
shapix/shapes/angle.py
shapix/shapes/circle.py
shapix/shapes/line.py
shapix/shapes/point.py
shapix/shapes/triangle.py
shapix/syntax/__init__.py
shapix/syntax/exporter.py
shapix/syntax/parser.py
shapix/utils/__init__.py
shapix-0.1.0.dist-info/licenses/LICENSE
shapix-0.1.0.dist-info/METADATA
shapix-0.1.0.dist-info/WHEEL
shapix-0.1.0.dist-info/entry_points.txt
shapix-0.1.0.dist-info/top_level.txt
shapix-0.1.0.dist-info/RECORD
