Metadata-Version: 2.4
Name: shapix
Version: 0.1.0
Summary: A geometry engine for Python with text-based syntax and PNG export
Home-page: https://github.com/berkayz/shapix
Author: BerkayZ
Author-email: BerkayZ <zelyurtberkay@gmail.com>
Project-URL: Homepage, https://github.com/BerkayZ/shapix
Project-URL: Bug Reports, https://github.com/BerkayZ/shapix/issues
Project-URL: Source, https://github.com/BerkayZ/shapix
Keywords: geometry,mathematics,visualization,education,graphics,shapes,canvas,png,export
Classifier: Development Status :: 3 - Alpha
Classifier: Intended Audience :: Developers
Classifier: Intended Audience :: Education
Classifier: Intended Audience :: Science/Research
Classifier: License :: OSI Approved :: MIT License
Classifier: Operating System :: OS Independent
Classifier: Programming Language :: Python :: 3
Classifier: Programming Language :: Python :: 3.8
Classifier: Programming Language :: Python :: 3.9
Classifier: Programming Language :: Python :: 3.10
Classifier: Programming Language :: Python :: 3.11
Classifier: Topic :: Scientific/Engineering :: Mathematics
Classifier: Topic :: Scientific/Engineering :: Visualization
Classifier: Topic :: Education
Classifier: Topic :: Multimedia :: Graphics
Requires-Python: >=3.8
License-File: LICENSE
Requires-Dist: pillow>=8.0.0
Provides-Extra: dev
Requires-Dist: pytest>=6.0; extra == "dev"
Requires-Dist: pytest-cov>=2.10; extra == "dev"
Requires-Dist: black>=21.0; extra == "dev"
Requires-Dist: flake8>=3.8; extra == "dev"
Requires-Dist: mypy>=0.910; extra == "dev"
Provides-Extra: gui
Dynamic: author
Dynamic: home-page
Dynamic: license-file
Dynamic: requires-python
